pyqaserver/MLC_fieldsize.py
pyqaserver/RestToolbox GNU v3.txt
pyqaserver/RestToolbox_modified.py
pyqaserver/__init__.py
pyqaserver/__main__.py
pyqaserver/administration.py
pyqaserver/analyze_dynalogs.py
pyqaserver/catphan_module.py
pyqaserver/config.py
pyqaserver/create_dynalog_database.py
pyqaserver/dynalog_module.py
pyqaserver/field_rotation.py
pyqaserver/fieldrot_module.py
pyqaserver/fieldsize_module.py
pyqaserver/flatsym_module.py
pyqaserver/general_functions.py
pyqaserver/general_routes.py
pyqaserver/general_settings_database.py
pyqaserver/imagereview_module.py
pyqaserver/picketfence_module.py
pyqaserver/planarimaging_module.py
pyqaserver/pyqaserver.py
pyqaserver/starshot_module.py
pyqaserver/trends.py
pyqaserver/trends_database.py
pyqaserver/version.py
pyqaserver/vmat_module.py
pyqaserver/winstonlutz_module.py
pyqaserver/python_packages/__init__.py
pyqaserver/python_packages/__pycache__/__init__.cpython-38.pyc
pyqaserver/python_packages/bottlepy/LICENSE
pyqaserver/python_packages/bottlepy/__init__.py
pyqaserver/python_packages/bottlepy/bottle.py
pyqaserver/python_packages/minimumboundingbox/LICENSE
pyqaserver/python_packages/minimumboundingbox/__init__.py
pyqaserver/python_packages/minimumboundingbox/minimumboundingbox.py
pyqaserver/python_packages/mpld3/AUTHORS.md
pyqaserver/python_packages/mpld3/CHANGES MADE.txt
pyqaserver/python_packages/mpld3/LICENSE.txt
pyqaserver/python_packages/mpld3/__about__.py
pyqaserver/python_packages/mpld3/__init__.py
pyqaserver/python_packages/mpld3/_display.py
pyqaserver/python_packages/mpld3/_server.py
pyqaserver/python_packages/mpld3/mpld3renderer.py
pyqaserver/python_packages/mpld3/plugins.py
pyqaserver/python_packages/mpld3/urls.py
pyqaserver/python_packages/mpld3/utils.py
pyqaserver/python_packages/mpld3/js/d3.v3.min.js
pyqaserver/python_packages/mpld3/js/mpld3.v0.3.js
pyqaserver/python_packages/mpld3/js/mpld3.v0.3.min.js
pyqaserver/python_packages/mpld3/mplexporter/__init__.py
pyqaserver-2.0.1.dist-info/LICENSE
pyqaserver-2.0.1.dist-info/METADATA
pyqaserver-2.0.1.dist-info/WHEEL
pyqaserver-2.0.1.dist-info/entry_points.txt
pyqaserver-2.0.1.dist-info/top_level.txt
pyqaserver-2.0.1.dist-info/RECORD
